MANIFEST.in
README.md
setup.py
django_rss2rest.egg-info/PKG-INFO
django_rss2rest.egg-info/SOURCES.txt
django_rss2rest.egg-info/dependency_links.txt
django_rss2rest.egg-info/requires.txt
django_rss2rest.egg-info/top_level.txt
rss2rest/__init__.py
rss2rest/abstract_models.py
rss2rest/api.py
rss2rest/models.py
rss2rest/parser.py
rss2rest/tests.py
rss2rest/views.py
rss2rest/management/__init__.py
rss2rest/management/commands/__init__.py
rss2rest/management/commands/syncrss2rest.py