Metadata-Version: 1.0
Name: django-rss2rest
Version: 0.1
Summary: RSS scraper with immediate RESTful access to feed items
Home-page: https://github.com/gump/rss2rest
Author: Michal Gump Szczesny
Author-email: gump@gump.tv
License: BSD
Keywords: Django,RSS,RESTful API
Platform: linux
Classifier: Environment :: Web Environment
Classifier: Framework :: Django
Classifier: Intended Audience :: Developers
Classifier: License :: OSI Approved :: BSD License
Classifier: Operating System :: Unix
Classifier: Programming Language :: Python
